jdb_py/__init__.py
jdb_py/main.py
jdb_py-0.1.0.dist-info/METADATA
jdb_py-0.1.0.dist-info/WHEEL
jdb_py-0.1.0.dist-info/entry_points.txt
jdb_py-0.1.0.dist-info/RECORD
