Metadata-Version: 2.1
Name: jdb-py
Version: 0.1.0
Summary: 这是一个用于补全 jdb 调试器的命令的工具
Home-page: https://github.com/xiliuya/jdb-py
Keywords: debugger,java
Author: xiliuya
Author-email: xiliuya@aliyun.com
Requires-Python: >=3.10,<4.0
Classifier: Programming Language :: Python :: 3
Classifier: Programming Language :: Python :: 3.10
Classifier: Programming Language :: Python :: 3.11
Requires-Dist: prompt-toolkit (>=3.0.38,<4.0.0)
Requires-Dist: pygments (>=2.14.0,<3.0.0)
Project-URL: Repository, https://github.com/xiliuya/jdb-py
